{
    "type": "object",
    "properties": {
        "id": {
            "type": "number"
        },
        "name": {
            "type": ["null","string"]
        },
        "email": {
            "type": ["null","string"]
        },
        "phone": {
            "type": ["null","string"]
        },
        "source": {
            "type": ["null","string"]
        },
        "created_at": {
            "type": ["null","string"],
            "format": "date-time"
        },
        "updated_at": {
            "type": ["null","string"],
            "format": "date-time"
        },
        "positive_ratings": {
            "type": ["null","number"]
        }
    }
}
